limpid/__init__.py
limpid/__main__.py
limpid/implantation.py
limpid/limpid.py
limpid/visualize.py
limpid/example_data/__init__.py
limpid/example_data/cu-si.csv
limpid/example_data/si.csv
limpid-0.4.2.dist-info/licenses/LICENSE
limpid-0.4.2.dist-info/METADATA
limpid-0.4.2.dist-info/WHEEL
limpid-0.4.2.dist-info/top_level.txt
limpid-0.4.2.dist-info/RECORD
