Metadata-Version: 2.4
Name: limpid
Version: 0.4.2
Summary: A package for fitting positron annihilation Doppler broadening depth profiles.
Author-email: Lucian Mathes <lucian.mathes@tum.de>
Classifier: Development Status :: 2 - Pre-Alpha
Classifier: Environment :: Console
Classifier: Intended Audience :: Science/Research
Classifier: License :: OSI Approved :: GNU General Public License v3 (GPLv3)
Classifier: Natural Language :: English
Classifier: Operating System :: OS Independent
Classifier: Programming Language :: Python :: 3
Classifier: Topic :: Scientific/Engineering :: Physics
Requires-Python: >=3.10
License-File: LICENSE
Requires-Dist: numpy>=2.1.0
Requires-Dist: scipy>=1.15.0
Requires-Dist: matplotlib>=3.9.0
Requires-Dist: numba>=0.61.0
Requires-Dist: lmfit>=1.3.3
Dynamic: license-file
